pyslha/__init__.py
pyslha/__main__.py
pyslha-3.3.2.data/scripts/isawig2slha
pyslha-3.3.2.data/scripts/slha2isawig
pyslha-3.3.2.data/scripts/slhaplot
pyslha-3.3.2.dist-info/licenses/LICENSE
pyslha-3.3.2.dist-info/METADATA
pyslha-3.3.2.dist-info/WHEEL
pyslha-3.3.2.dist-info/top_level.txt
pyslha-3.3.2.dist-info/RECORD
