Metadata-Version: 2.4
Name: pyslha
Version: 3.3.2
Summary: Parsing, manipulating, and visualising SUSY Les Houches Accord data
Author-email: Andy Buckley <andy.buckley@glasgow.ac.uk>
Project-URL: Homepage, http://www.insectnation.org/projects/pyslha
Project-URL: Bug Tracker, https://gitlab.com/hepcedar/pyslha/-/issues
Keywords: supersymmetry,susy,slha,simulation,mass,decay,hep,physics,particle
Classifier: Programming Language :: Python :: 3
Classifier: License :: OSI Approved :: GNU General Public License v3 (GPLv3)
Classifier: Operating System :: OS Independent
Classifier: Topic :: Scientific/Engineering :: Information Analysis
Classifier: Topic :: Scientific/Engineering :: Physics
Requires-Python: >=3.7
License-File: LICENSE
Requires-Dist: tex2pix>=0.1.5
Dynamic: license-file
